{"BTC-USDT":{"poloniex-liqui":[{"market":"BTC-USDT","percent":0.92,"profit":0.486,"direction":"poloniex-liqui","time":"09:08:15","quantity":0.0075,"buy":{"price":6960.88,"num":0.00752,"total":52.346},"sell":{"price":7066.98,"num":0.0075,"total":52.832}},{"market":"BTC-USDT","percent":0.92,"profit":0.486,"direction":"poloniex-liqui","time":"09:08:17","quantity":0.0075,"buy":{"price":6960.88,"num":0.00752,"total":52.346},"sell":{"price":7066.98,"num":0.0075,"total":52.832}},{"market":"BTC-USDT","percent":0.92,"profit":0.486,"direction":"poloniex-liqui","time":"09:08:20","quantity":0.0075,"buy":{"price":6960.88,"num":0.00752,"total":52.346},"sell":{"price":7066.98,"num":0.0075,"total":52.832}},{"market":"BTC-USDT","percent":0.93,"profit":0.4867,"direction":"poloniex-liqui","time":"09:08:23","quantity":0.0075,"buy":{"price":6960.78,"num":0.00752,"total":52.346},"sell":{"price":7066.98,"num":0.0075,"total":52.832}},{"market":"BTC-USDT","percent":0.93,"profit":0.4867,"direction":"poloniex-liqui","time":"09:08:25","quantity":0.0075,"buy":{"price":6960.78,"num":0.00752,"total":52.346},"sell":{"price":7066.98,"num":0.0075,"total":52.832}},{"market":"BTC-USDT","percent":0.93,"profit":0.4867,"direction":"poloniex-liqui","time":"09:08:27","quantity":0.0075,"buy":{"price":6960.78,"num":0.00752,"total":52.346},"sell":{"price":7066.98,"num":0.0075,"total":52.832}},{"market":"BTC-USDT","percent":0.93,"profit":0.4885,"direction":"poloniex-liqui","time":"09:08:30","quantity":0.0075,"buy":{"price":6960.55,"num":0.00752,"total":52.344},"sell":{"price":7066.98,"num":0.0075,"total":52.832}},{"market":"BTC-USDT","percent":0.93,"profit":0.4885,"direction":"poloniex-liqui","time":"09:08:32","quantity":0.0075,"buy":{"price":6960.55,"num":0.00752,"total":52.344},"sell":{"price":7066.98,"num":0.0075,"total":52.832}},{"market":"BTC-USDT","percent":0.93,"profit":0.4885,"direction":"poloniex-liqui","time":"09:08:34","quantity":0.0075,"buy":{"price":6960.55,"num":0.00752,"total":52.344},"sell":{"price":7066.98,"num":0.0075,"total":52.832}},{"market":"BTC-USDT","percent":0.94,"profit":0.4926,"direction":"poloniex-liqui","time":"09:08:37","quantity":0.0075,"buy":{"price":6960,"num":0.00752,"total":52.34},"sell":{"price":7066.98,"num":0.0075,"total":52.832}},{"market":"BTC-USDT","percent":0.94,"profit":0.4926,"direction":"poloniex-liqui","time":"09:08:39","quantity":0.0075,"buy":{"price":6960,"num":0.00752,"total":52.34},"sell":{"price":7066.98,"num":0.0075,"total":52.832}},{"market":"BTC-USDT","percent":0.95,"profit":0.4979,"direction":"poloniex-liqui","time":"09:08:42","quantity":0.0075,"buy":{"price":6960,"num":0.00752,"total":52.34},"sell":{"price":7067.69,"num":0.0075,"total":52.838}},{"market":"BTC-USDT","percent":0.95,"profit":0.4979,"direction":"poloniex-liqui","time":"09:08:45","quantity":0.0075,"buy":{"price":6960,"num":0.00752,"total":52.34},"sell":{"price":7067.69,"num":0.0075,"total":52.838}},{"market":"BTC-USDT","percent":0.95,"profit":0.4979,"direction":"poloniex-liqui","time":"09:08:47","quantity":0.0075,"buy":{"price":6960,"num":0.00752,"total":52.34},"sell":{"price":7067.69,"num":0.0075,"total":52.838}},{"market":"BTC-USDT","percent":0.95,"profit":0.4979,"direction":"poloniex-liqui","time":"09:08:50","quantity":0.0075,"buy":{"price":6960,"num":0.00752,"total":52.34},"sell":{"price":7067.69,"num":0.0075,"total":52.838}},{"market":"BTC-USDT","percent":0.95,"profit":0.4979,"direction":"poloniex-liqui","time":"09:08:52","quantity":0.0075,"buy":{"price":6960,"num":0.00752,"total":52.34},"sell":{"price":7067.69,"num":0.0075,"total":52.838}},{"market":"BTC-USDT","percent":0.95,"profit":0.4979,"direction":"poloniex-liqui","time":"09:08:54","quantity":0.0075,"buy":{"price":6960,"num":0.00752,"total":52.34},"sell":{"price":7067.69,"num":0.0075,"total":52.838}},{"market":"BTC-USDT","percent":0.95,"profit":0.4979,"direction":"poloniex-liqui","time":"09:08:56","quantity":0.0075,"buy":{"price":6960,"num":0.00752,"total":52.34},"sell":{"price":7067.69,"num":0.0075,"total":52.838}},{"market":"BTC-USDT","percent":0.95,"profit":0.4979,"direction":"poloniex-liqui","time":"09:08:59","quantity":0.0075,"buy":{"price":6960,"num":0.00752,"total":52.34},"sell":{"price":7067.69,"num":0.0075,"total":52.838}},{"market":"BTC-USDT","percent":0.95,"profit":0.4979,"direction":"poloniex-liqui","time":"09:09:01","quantity":0.0075,"buy":{"price":6960,"num":0.00752,"total":52.34},"sell":{"price":7067.69,"num":0.0075,"total":52.838}},{"market":"BTC-USDT","percent":0.95,"profit":0.4979,"direction":"poloniex-liqui","time":"09:09:03","quantity":0.0075,"buy":{"price":6960,"num":0.00752,"total":52.34},"sell":{"price":7067.69,"num":0.0075,"total":52.838}},{"market":"BTC-USDT","percent":0.95,"profit":0.4979,"direction":"poloniex-liqui","time":"09:09:06","quantity":0.0075,"buy":{"price":6960,"num":0.00752,"total":52.34},"sell":{"price":7067.69,"num":0.0075,"total":52.838}},{"market":"BTC-USDT","percent":0.95,"profit":0.4979,"direction":"poloniex-liqui","time":"09:09:08","quantity":0.0075,"buy":{"price":6960,"num":0.00752,"total":52.34},"sell":{"price":7067.69,"num":0.0075,"total":52.838}},{"market":"BTC-USDT","percent":0.95,"profit":0.4979,"direction":"poloniex-liqui","time":"09:09:10","quantity":0.0075,"buy":{"price":6960,"num":0.00752,"total":52.34},"sell":{"price":7067.69,"num":0.0075,"total":52.838}},{"market":"BTC-USDT","percent":0.95,"profit":0.4979,"direction":"poloniex-liqui","time":"09:09:13","quantity":0.0075,"buy":{"price":6960,"num":0.00752,"total":52.34},"sell":{"price":7067.69,"num":0.0075,"total":52.838}},{"market":"BTC-USDT","percent":0.95,"profit":0.4979,"direction":"poloniex-liqui","time":"09:09:15","quantity":0.0075,"buy":{"price":6960,"num":0.00752,"total":52.34},"sell":{"price":7067.69,"num":0.0075,"total":52.838}},{"market":"BTC-USDT","percent":0.95,"profit":0.4979,"direction":"poloniex-liqui","time":"09:09:18","quantity":0.0075,"buy":{"price":6960,"num":0.00752,"total":52.34},"sell":{"price":7067.69,"num":0.0075,"total":52.838}},{"market":"BTC-USDT","percent":0.95,"profit":0.4979,"direction":"poloniex-liqui","time":"09:09:21","quantity":0.0075,"buy":{"price":6960,"num":0.00752,"total":52.338},"sell":{"price":7066.28,"num":0.0075,"total":52.836}},{"market":"BTC-USDT","percent":0.93,"profit":0.489,"direction":"poloniex-liqui","time":"09:09:24","quantity":0.0075,"buy":{"price":6960.98,"num":0.00752,"total":52.347},"sell":{"price":7066.28,"num":0.0075,"total":52.836}},{"market":"BTC-USDT","percent":0.93,"profit":0.489,"direction":"poloniex-liqui","time":"09:09:27","quantity":0.0075,"buy":{"price":6960.98,"num":0.00752,"total":52.347},"sell":{"price":7066.28,"num":0.0075,"total":52.836}},{"market":"BTC-USDT","percent":0.91,"profit":0.4799,"direction":"poloniex-liqui","time":"09:09:29","quantity":0.0075,"buy":{"price":6960.98,"num":0.00752,"total":52.347},"sell":{"price":7066.28,"num":0.0075,"total":52.827}},{"market":"BTC-USDT","percent":0.91,"profit":0.4799,"direction":"poloniex-liqui","time":"09:09:32","quantity":0.0075,"buy":{"price":6960.98,"num":0.00752,"total":52.347},"sell":{"price":7066.28,"num":0.0075,"total":52.827}},{"market":"BTC-USDT","percent":0.92,"profit":0.4814,"direction":"poloniex-liqui","time":"09:09:35","quantity":0.0075,"buy":{"price":6960.98,"num":0.00752,"total":52.347},"sell":{"price":7066.28,"num":0.0075,"total":52.829}},{"market":"BTC-USDT","percent":0.92,"profit":0.4814,"direction":"poloniex-liqui","time":"09:09:37","quantity":0.0075,"buy":{"price":6960.98,"num":0.00752,"total":52.347},"sell":{"price":7066.28,"num":0.0075,"total":52.829}},{"market":"BTC-USDT","percent":0.92,"profit":0.4814,"direction":"poloniex-liqui","time":"09:09:39","quantity":0.0075,"buy":{"price":6960.98,"num":0.00752,"total":52.347},"sell":{"price":7066.28,"num":0.0075,"total":52.829}},{"market":"BTC-USDT","percent":0.94,"profit":0.4958,"direction":"poloniex-liqui","time":"09:09:41","quantity":0.0075,"buy":{"price":6960.98,"num":0.00752,"total":52.347},"sell":{"price":7068.4,"num":0.0075,"total":52.843}},{"market":"BTC-USDT","percent":0.94,"profit":0.4958,"direction":"poloniex-liqui","time":"09:09:43","quantity":0.0075,"buy":{"price":6960.98,"num":0.00752,"total":52.347},"sell":{"price":7068.4,"num":0.0075,"total":52.843}},{"market":"BTC-USDT","percent":0.94,"profit":0.4958,"direction":"poloniex-liqui","time":"09:09:46","quantity":0.0075,"buy":{"price":6960.98,"num":0.00752,"total":52.347},"sell":{"price":7068.4,"num":0.0075,"total":52.843}},{"market":"BTC-USDT","percent":0.94,"profit":0.4958,"direction":"poloniex-liqui","time":"09:09:48","quantity":0.0075,"buy":{"price":6960.98,"num":0.00752,"total":52.347},"sell":{"price":7068.4,"num":0.0075,"total":52.843}},{"market":"BTC-USDT","percent":0.94,"profit":0.4958,"direction":"poloniex-liqui","time":"09:09:50","quantity":0.0075,"buy":{"price":6960.98,"num":0.00752,"total":52.347},"sell":{"price":7068.4,"num":0.0075,"total":52.843}},{"market":"BTC-USDT","percent":0.94,"profit":0.4958,"direction":"poloniex-liqui","time":"09:09:53","quantity":0.0075,"buy":{"price":6960.98,"num":0.00752,"total":52.347},"sell":{"price":7068.4,"num":0.0075,"total":52.843}},{"market":"BTC-USDT","percent":0.94,"profit":0.4958,"direction":"poloniex-liqui","time":"09:09:55","quantity":0.0075,"buy":{"price":6960.98,"num":0.00752,"total":52.347},"sell":{"price":7068.4,"num":0.0075,"total":52.843}},{"market":"BTC-USDT","percent":0.94,"profit":0.4958,"direction":"poloniex-liqui","time":"09:09:57","quantity":0.0075,"buy":{"price":6960.98,"num":0.00752,"total":52.347},"sell":{"price":7068.4,"num":0.0075,"total":52.843}},{"market":"BTC-USDT","percent":0.94,"profit":0.4958,"direction":"poloniex-liqui","time":"09:10:00","quantity":0.0075,"buy":{"price":6960.98,"num":0.00752,"total":52.347},"sell":{"price":7068.4,"num":0.0075,"total":52.843}},{"market":"BTC-USDT","percent":0.94,"profit":0.4958,"direction":"poloniex-liqui","time":"09:10:03","quantity":0.0075,"buy":{"price":6960.98,"num":0.00752,"total":52.347},"sell":{"price":7068.4,"num":0.0075,"total":52.843}},{"market":"BTC-USDT","percent":0.94,"profit":0.4958,"direction":"poloniex-liqui","time":"09:10:06","quantity":0.0075,"buy":{"price":6960.98,"num":0.00752,"total":52.347},"sell":{"price":7068.4,"num":0.0075,"total":52.843}},{"market":"BTC-USDT","percent":0.94,"profit":0.4958,"direction":"poloniex-liqui","time":"09:10:08","quantity":0.0075,"buy":{"price":6960.98,"num":0.00752,"total":52.347},"sell":{"price":7068.4,"num":0.0075,"total":52.843}},{"market":"BTC-USDT","percent":0.94,"profit":0.4958,"direction":"poloniex-liqui","time":"09:10:10","quantity":0.0075,"buy":{"price":6960.98,"num":0.00752,"total":52.347},"sell":{"price":7068.4,"num":0.0075,"total":52.843}},{"market":"BTC-USDT","percent":0.94,"profit":0.4966,"direction":"poloniex-liqui","time":"09:10:12","quantity":0.0075,"buy":{"price":6960.98,"num":0.00752,"total":52.346},"sell":{"price":7068.4,"num":0.0075,"total":52.843}},{"market":"BTC-USDT","percent":0.94,"profit":0.4958,"direction":"poloniex-liqui","time":"09:10:14","quantity":0.0075,"buy":{"price":6960.98,"num":0.00752,"total":52.347},"sell":{"price":7068.4,"num":0.0075,"total":52.843}},{"market":"BTC-USDT","percent":0.92,"profit":0.4819,"direction":"poloniex-liqui","time":"09:10:17","quantity":0.0075,"buy":{"price":6960.98,"num":0.00752,"total":52.347},"sell":{"price":7066.28,"num":0.0075,"total":52.829}},{"market":"BTC-USDT","percent":0.92,"profit":0.4819,"direction":"poloniex-liqui","time":"09:10:19","quantity":0.0075,"buy":{"price":6960.98,"num":0.00752,"total":52.347},"sell":{"price":7066.28,"num":0.0075,"total":52.829}},{"market":"BTC-USDT","percent":0.92,"profit":0.4819,"direction":"poloniex-liqui","time":"09:10:21","quantity":0.0075,"buy":{"price":6960.98,"num":0.00752,"total":52.347},"sell":{"price":7066.28,"num":0.0075,"total":52.829}},{"market":"BTC-USDT","percent":0.92,"profit":0.4819,"direction":"poloniex-liqui","time":"09:10:24","quantity":0.0075,"buy":{"price":6960.98,"num":0.00752,"total":52.347},"sell":{"price":7066.28,"num":0.0075,"total":52.829}},{"market":"BTC-USDT","percent":0.92,"profit":0.4814,"direction":"poloniex-liqui","time":"09:10:26","quantity":0.0075,"buy":{"price":6960.98,"num":0.00752,"total":52.347},"sell":{"price":7066.28,"num":0.0075,"total":52.829}},{"market":"BTC-USDT","percent":0.92,"profit":0.4814,"direction":"poloniex-liqui","time":"09:10:29","quantity":0.0075,"buy":{"price":6960.98,"num":0.00752,"total":52.347},"sell":{"price":7066.28,"num":0.0075,"total":52.829}},{"market":"BTC-USDT","percent":0.92,"profit":0.4814,"direction":"poloniex-liqui","time":"09:10:31","quantity":0.0075,"buy":{"price":6960.98,"num":0.00752,"total":52.347},"sell":{"price":7066.28,"num":0.0075,"total":52.829}},{"market":"BTC-USDT","percent":0.92,"profit":0.4814,"direction":"poloniex-liqui","time":"09:10:34","quantity":0.0075,"buy":{"price":6960.98,"num":0.00752,"total":52.347},"sell":{"price":7066.28,"num":0.0075,"total":52.829}},{"market":"BTC-USDT","percent":0.99,"profit":0.5198,"direction":"poloniex-liqui","time":"09:10:37","quantity":0.0075,"buy":{"price":6955.88,"num":0.00752,"total":52.309},"sell":{"price":7066.28,"num":0.0075,"total":52.829}},{"market":"BTC-USDT","percent":0.92,"profit":0.4814,"direction":"poloniex-liqui","time":"09:10:39","quantity":0.0075,"buy":{"price":6960.98,"num":0.00752,"total":52.347},"sell":{"price":7066.28,"num":0.0075,"total":52.829}},{"market":"BTC-USDT","percent":0.99,"profit":0.5221,"direction":"poloniex-liqui","time":"09:10:41","quantity":0.0075,"buy":{"price":6955.57,"num":0.00752,"total":52.306},"sell":{"price":7066.28,"num":0.0075,"total":52.829}},{"market":"BTC-USDT","percent":1.02,"profit":0.5365,"direction":"poloniex-liqui","time":"09:10:43","quantity":0.0075,"buy":{"price":6955.57,"num":0.00752,"total":52.306},"sell":{"price":7068.4,"num":0.0075,"total":52.843}},{"market":"BTC-USDT","percent":1.02,"profit":0.5365,"direction":"poloniex-liqui","time":"09:10:46","quantity":0.0075,"buy":{"price":6955.57,"num":0.00752,"total":52.306},"sell":{"price":7068.4,"num":0.0075,"total":52.843}},{"market":"BTC-USDT","percent":1.02,"profit":0.5365,"direction":"poloniex-liqui","time":"09:10:48","quantity":0.0075,"buy":{"price":6955.57,"num":0.00752,"total":52.306},"sell":{"price":7068.4,"num":0.0075,"total":52.843}},{"market":"BTC-USDT","percent":1.02,"profit":0.5365,"direction":"poloniex-liqui","time":"09:10:51","quantity":0.0075,"buy":{"price":6955.57,"num":0.00752,"total":52.306},"sell":{"price":7068.4,"num":0.0075,"total":52.843}},{"market":"BTC-USDT","percent":1.02,"profit":0.5365,"direction":"poloniex-liqui","time":"09:10:53","quantity":0.0075,"buy":{"price":6955.57,"num":0.00752,"total":52.306},"sell":{"price":7068.4,"num":0.0075,"total":52.843}},{"market":"BTC-USDT","percent":1.02,"profit":0.5365,"direction":"poloniex-liqui","time":"09:10:56","quantity":0.0075,"buy":{"price":6955.57,"num":0.00752,"total":52.306},"sell":{"price":7068.4,"num":0.0075,"total":52.843}},{"market":"BTC-USDT","percent":1.02,"profit":0.5365,"direction":"poloniex-liqui","time":"09:10:59","quantity":0.0075,"buy":{"price":6955.57,"num":0.00752,"total":52.306},"sell":{"price":7068.4,"num":0.0075,"total":52.843}},{"market":"BTC-USDT","percent":1.02,"profit":0.5365,"direction":"poloniex-liqui","time":"09:11:01","quantity":0.0075,"buy":{"price":6955.57,"num":0.00752,"total":52.306},"sell":{"price":7068.4,"num":0.0075,"total":52.843}},{"market":"BTC-USDT","percent":1.02,"profit":0.5365,"direction":"poloniex-liqui","time":"09:11:04","quantity":0.0075,"buy":{"price":6955.57,"num":0.00752,"total":52.306},"sell":{"price":7068.4,"num":0.0075,"total":52.843}},{"market":"BTC-USDT","percent":1.02,"profit":0.5365,"direction":"poloniex-liqui","time":"09:11:06","quantity":0.0075,"buy":{"price":6955.57,"num":0.00752,"total":52.306},"sell":{"price":7068.4,"num":0.0075,"total":52.843}},{"market":"BTC-USDT","percent":1.1,"profit":0.5784,"direction":"poloniex-liqui","time":"09:11:08","quantity":0.0075,"buy":{"price":6950,"num":0.00752,"total":52.265},"sell":{"price":7068.4,"num":0.0075,"total":52.843}},{"market":"BTC-USDT","percent":1.1,"profit":0.5784,"direction":"poloniex-liqui","time":"09:11:11","quantity":0.0075,"buy":{"price":6950,"num":0.00752,"total":52.265},"sell":{"price":7068.4,"num":0.0075,"total":52.843}},{"market":"BTC-USDT","percent":1.07,"profit":0.564,"direction":"poloniex-liqui","time":"09:11:13","quantity":0.0075,"buy":{"price":6950,"num":0.00752,"total":52.265},"sell":{"price":7066.28,"num":0.0075,"total":52.829}},{"market":"BTC-USDT","percent":0.99,"profit":0.5221,"direction":"poloniex-liqui","time":"09:11:16","quantity":0.0075,"buy":{"price":6955.57,"num":0.00752,"total":52.306},"sell":{"price":7066.28,"num":0.0075,"total":52.829}},{"market":"BTC-USDT","percent":0.92,"profit":0.4814,"direction":"poloniex-liqui","time":"09:11:18","quantity":0.0075,"buy":{"price":6960.98,"num":0.00752,"total":52.347},"sell":{"price":7066.28,"num":0.0075,"total":52.829}},{"market":"BTC-USDT","percent":0.92,"profit":0.4814,"direction":"poloniex-liqui","time":"09:11:20","quantity":0.0075,"buy":{"price":6960.98,"num":0.00752,"total":52.347},"sell":{"price":7066.28,"num":0.0075,"total":52.829}},{"market":"BTC-USDT","percent":0.99,"profit":0.5194,"direction":"poloniex-liqui","time":"09:11:22","quantity":0.0075,"buy":{"price":6955.94,"num":0.00752,"total":52.309},"sell":{"price":7066.28,"num":0.0075,"total":52.829}},{"market":"BTC-USDT","percent":0.99,"profit":0.5194,"direction":"poloniex-liqui","time":"09:11:25","quantity":0.0075,"buy":{"price":6955.94,"num":0.00752,"total":52.309},"sell":{"price":7066.28,"num":0.0075,"total":52.829}},{"market":"BTC-USDT","percent":0.99,"profit":0.5194,"direction":"poloniex-liqui","time":"09:11:27","quantity":0.0075,"buy":{"price":6955.94,"num":0.00752,"total":52.309},"sell":{"price":7066.28,"num":0.0075,"total":52.829}},{"market":"BTC-USDT","percent":0.99,"profit":0.5194,"direction":"poloniex-liqui","time":"09:11:30","quantity":0.0075,"buy":{"price":6955.94,"num":0.00752,"total":52.309},"sell":{"price":7066.28,"num":0.0075,"total":52.829}},{"market":"BTC-USDT","percent":0.99,"profit":0.5194,"direction":"poloniex-liqui","time":"09:11:32","quantity":0.0075,"buy":{"price":6955.94,"num":0.00752,"total":52.309},"sell":{"price":7066.28,"num":0.0075,"total":52.829}},{"market":"BTC-USDT","percent":0.99,"profit":0.5194,"direction":"poloniex-liqui","time":"09:11:34","quantity":0.0075,"buy":{"price":6955.94,"num":0.00752,"total":52.309},"sell":{"price":7066.28,"num":0.0075,"total":52.829}},{"market":"BTC-USDT","percent":0.99,"profit":0.5194,"direction":"poloniex-liqui","time":"09:11:36","quantity":0.0075,"buy":{"price":6955.94,"num":0.00752,"total":52.309},"sell":{"price":7066.28,"num":0.0075,"total":52.829}},{"market":"BTC-USDT","percent":0.99,"profit":0.5194,"direction":"poloniex-liqui","time":"09:11:39","quantity":0.0075,"buy":{"price":6955.94,"num":0.00752,"total":52.309},"sell":{"price":7066.28,"num":0.0075,"total":52.829}},{"market":"BTC-USDT","percent":0.99,"profit":0.5194,"direction":"poloniex-liqui","time":"09:11:41","quantity":0.0075,"buy":{"price":6955.94,"num":0.00752,"total":52.309},"sell":{"price":7066.28,"num":0.0075,"total":52.829}},{"market":"BTC-USDT","percent":1.02,"profit":0.5337,"direction":"poloniex-liqui","time":"09:11:44","quantity":0.0075,"buy":{"price":6955.94,"num":0.00752,"total":52.309},"sell":{"price":7068.4,"num":0.0075,"total":52.843}},{"market":"BTC-USDT","percent":1.02,"profit":0.5337,"direction":"poloniex-liqui","time":"09:11:46","quantity":0.0075,"buy":{"price":6955.94,"num":0.00752,"total":52.309},"sell":{"price":7068.4,"num":0.0075,"total":52.843}},{"market":"BTC-USDT","percent":1.02,"profit":0.5337,"direction":"poloniex-liqui","time":"09:11:49","quantity":0.0075,"buy":{"price":6955.94,"num":0.00752,"total":52.309},"sell":{"price":7068.4,"num":0.0075,"total":52.843}},{"market":"BTC-USDT","percent":1.02,"profit":0.5337,"direction":"poloniex-liqui","time":"09:11:51","quantity":0.0075,"buy":{"price":6955.94,"num":0.00752,"total":52.309},"sell":{"price":7068.4,"num":0.0075,"total":52.843}},{"market":"BTC-USDT","percent":1.02,"profit":0.5337,"direction":"poloniex-liqui","time":"09:11:53","quantity":0.0075,"buy":{"price":6955.94,"num":0.00752,"total":52.309},"sell":{"price":7068.4,"num":0.0075,"total":52.843}},{"market":"BTC-USDT","percent":1.02,"profit":0.5365,"direction":"poloniex-liqui","time":"09:11:56","quantity":0.0075,"buy":{"price":6955.57,"num":0.00752,"total":52.306},"sell":{"price":7068.4,"num":0.0075,"total":52.843}},{"market":"BTC-USDT","percent":1.02,"profit":0.5365,"direction":"poloniex-liqui","time":"09:11:59","quantity":0.0075,"buy":{"price":6955.57,"num":0.00752,"total":52.306},"sell":{"price":7068.4,"num":0.0075,"total":52.843}},{"market":"BTC-USDT","percent":1.02,"profit":4.2708,"direction":"poloniex-liqui","time":"09:12:01","quantity":0.06,"buy":{"price":6955.57,"num":0.060161,"total":418.451},"sell":{"price":7068.04,"num":0.06,"total":422.722}},{"market":"BTC-USDT","percent":0.99,"profit":0.5221,"direction":"poloniex-liqui","time":"09:12:03","quantity":0.0075,"buy":{"price":6955.57,"num":0.00752,"total":52.306},"sell":{"price":7066.28,"num":0.0075,"total":52.829}},{"market":"BTC-USDT","percent":0.99,"profit":0.5221,"direction":"poloniex-liqui","time":"09:12:06","quantity":0.0075,"buy":{"price":6955.57,"num":0.00752,"total":52.306},"sell":{"price":7066.28,"num":0.0075,"total":52.829}},{"market":"BTC-USDT","percent":0.99,"profit":0.5221,"direction":"poloniex-liqui","time":"09:12:08","quantity":0.0075,"buy":{"price":6955.57,"num":0.00752,"total":52.306},"sell":{"price":7066.28,"num":0.0075,"total":52.829}},{"market":"BTC-USDT","percent":0.99,"profit":0.5221,"direction":"poloniex-liqui","time":"09:12:10","quantity":0.0075,"buy":{"price":6955.57,"num":0.00752,"total":52.306},"sell":{"price":7066.28,"num":0.0075,"total":52.829}},{"market":"BTC-USDT","percent":0.99,"profit":0.5221,"direction":"poloniex-liqui","time":"09:12:13","quantity":0.0075,"buy":{"price":6955.57,"num":0.00752,"total":52.306},"sell":{"price":7066.28,"num":0.0075,"total":52.829}},{"market":"BTC-USDT","percent":0.99,"profit":0.5221,"direction":"poloniex-liqui","time":"09:12:15","quantity":0.0075,"buy":{"price":6955.57,"num":0.00752,"total":52.306},"sell":{"price":7066.28,"num":0.0075,"total":52.829}},{"market":"BTC-USDT","percent":0.99,"profit":0.5221,"direction":"poloniex-liqui","time":"09:12:17","quantity":0.0075,"buy":{"price":6955.57,"num":0.00752,"total":52.306},"sell":{"price":7066.28,"num":0.0075,"total":52.829}},{"market":"BTC-USDT","percent":0.99,"profit":0.5221,"direction":"poloniex-liqui","time":"09:12:20","quantity":0.0075,"buy":{"price":6955.57,"num":0.00752,"total":52.306},"sell":{"price":7066.28,"num":0.0075,"total":52.829}},{"market":"BTC-USDT","percent":0.99,"profit":0.5221,"direction":"poloniex-liqui","time":"09:12:22","quantity":0.0075,"buy":{"price":6955.57,"num":0.00752,"total":52.306},"sell":{"price":7066.28,"num":0.0075,"total":52.829}},{"market":"BTC-USDT","percent":0.99,"profit":0.5221,"direction":"poloniex-liqui","time":"09:12:24","quantity":0.0075,"buy":{"price":6955.57,"num":0.00752,"total":52.306},"sell":{"price":7066.28,"num":0.0075,"total":52.829}},{"market":"BTC-USDT","percent":0.99,"profit":0.5221,"direction":"poloniex-liqui","time":"09:12:26","quantity":0.0075,"buy":{"price":6955.57,"num":0.00752,"total":52.306},"sell":{"price":7066.28,"num":0.0075,"total":52.829}},{"market":"BTC-USDT","percent":0.99,"profit":0.5221,"direction":"poloniex-liqui","time":"09:12:29","quantity":0.0075,"buy":{"price":6955.57,"num":0.00752,"total":52.306},"sell":{"price":7066.28,"num":0.0075,"total":52.829}},{"market":"BTC-USDT","percent":0.99,"profit":0.5221,"direction":"poloniex-liqui","time":"09:12:31","quantity":0.0075,"buy":{"price":6955.57,"num":0.00752,"total":52.306},"sell":{"price":7066.28,"num":0.0075,"total":52.829}},{"market":"BTC-USDT","percent":0.99,"profit":0.5211,"direction":"poloniex-liqui","time":"09:12:34","quantity":0.0075,"buy":{"price":6955.57,"num":0.00752,"total":52.306},"sell":{"price":7066.28,"num":0.0075,"total":52.827}},{"market":"BTC-USDT","percent":0.99,"profit":0.5211,"direction":"poloniex-liqui","time":"09:12:36","quantity":0.0075,"buy":{"price":6955.57,"num":0.00752,"total":52.306},"sell":{"price":7066.28,"num":0.0075,"total":52.827}},{"market":"BTC-USDT","percent":1.02,"profit":0.5377,"direction":"poloniex-liqui","time":"09:12:38","quantity":0.0075,"buy":{"price":6953.36,"num":0.00752,"total":52.29},"sell":{"price":7066.28,"num":0.0075,"total":52.827}},{"market":"BTC-USDT","percent":1.14,"profit":0.5971,"direction":"poloniex-liqui","time":"09:12:40","quantity":0.0075,"buy":{"price":6953.36,"num":0.00752,"total":52.23},"sell":{"price":7066.28,"num":0.0075,"total":52.827}},{"market":"BTC-USDT","percent":1.14,"profit":0.5971,"direction":"poloniex-liqui","time":"09:12:43","quantity":0.0075,"buy":{"price":6953.36,"num":0.00752,"total":52.23},"sell":{"price":7066.28,"num":0.0075,"total":52.827}},{"market":"BTC-USDT","percent":1.14,"profit":0.5971,"direction":"poloniex-liqui","time":"09:12:45","quantity":0.0075,"buy":{"price":6953.36,"num":0.00752,"total":52.23},"sell":{"price":7066.28,"num":0.0075,"total":52.827}}]}}