{"BTC-USDT":{"binance-poloniex":[{"market":"BTC-USDT","percent":0.35,"profit":0.7605,"direction":"binance-poloniex","time":"15:54:10","quantity":0.0375,"buy":{"price":5733.03,"num":0.03756259,"total":215.34746559},"sell":{"price":5774.1,"num":0.0375,"total":216.1079623}},{"market":"BTC-USDT","percent":0.35,"profit":0.1521,"direction":"binance-poloniex","time":"15:54:13","quantity":0.0075,"buy":{"price":5733.03,"num":0.00751252,"total":43.06949312},"sell":{"price":5774.1,"num":0.0075,"total":43.22159246}},{"market":"BTC-USDT","percent":0.35,"profit":0.7605,"direction":"binance-poloniex","time":"15:54:17","quantity":0.0375,"buy":{"price":5733.03,"num":0.03756259,"total":215.34746559},"sell":{"price":5774.1,"num":0.0375,"total":216.1079623}},{"market":"BTC-USDT","percent":0.35,"profit":0.7605,"direction":"binance-poloniex","time":"15:54:20","quantity":0.0375,"buy":{"price":5733.03,"num":0.03756259,"total":215.34746559},"sell":{"price":5774.1,"num":0.0375,"total":216.1079623}},{"market":"BTC-USDT","percent":0.35,"profit":0.7605,"direction":"binance-poloniex","time":"15:54:24","quantity":0.0375,"buy":{"price":5733.03,"num":0.03756259,"total":215.34746559},"sell":{"price":5774.1,"num":0.0375,"total":216.1079623}},{"market":"BTC-USDT","percent":0.35,"profit":0.7605,"direction":"binance-poloniex","time":"15:54:27","quantity":0.0375,"buy":{"price":5733.03,"num":0.03756259,"total":215.34746559},"sell":{"price":5774.1,"num":0.0375,"total":216.1079623}},{"market":"BTC-USDT","percent":0.35,"profit":0.7612,"direction":"binance-poloniex","time":"15:54:31","quantity":0.0375,"buy":{"price":5733.01,"num":0.03756259,"total":215.34671434},"sell":{"price":5774.1,"num":0.0375,"total":216.1079623}},{"market":"BTC-USDT","percent":0.35,"profit":0.7605,"direction":"binance-poloniex","time":"15:54:34","quantity":0.0375,"buy":{"price":5733.03,"num":0.03756259,"total":215.34746559},"sell":{"price":5774.1,"num":0.0375,"total":216.1079623}},{"market":"BTC-USDT","percent":0.35,"profit":0.7605,"direction":"binance-poloniex","time":"15:54:38","quantity":0.0375,"buy":{"price":5733.03,"num":0.03756259,"total":215.34746559},"sell":{"price":5774.1,"num":0.0375,"total":216.1079623}},{"market":"BTC-USDT","percent":0.35,"profit":0.7605,"direction":"binance-poloniex","time":"15:54:41","quantity":0.0375,"buy":{"price":5733.03,"num":0.03756259,"total":215.34746559},"sell":{"price":5774.1,"num":0.0375,"total":216.1079623}},{"market":"BTC-USDT","percent":0.35,"profit":0.7605,"direction":"binance-poloniex","time":"15:54:44","quantity":0.0375,"buy":{"price":5733.03,"num":0.03756259,"total":215.34746559},"sell":{"price":5774.1,"num":0.0375,"total":216.1079623}},{"market":"BTC-USDT","percent":0.35,"profit":0.7605,"direction":"binance-poloniex","time":"15:54:48","quantity":0.0375,"buy":{"price":5733.03,"num":0.03756259,"total":215.34746559},"sell":{"price":5774.1,"num":0.0375,"total":216.1079623}},{"market":"BTC-USDT","percent":0.35,"profit":0.7605,"direction":"binance-poloniex","time":"15:54:51","quantity":0.0375,"buy":{"price":5733.03,"num":0.03756259,"total":215.34746559},"sell":{"price":5774.1,"num":0.0375,"total":216.1079623}},{"market":"BTC-USDT","percent":0.35,"profit":0.7605,"direction":"binance-poloniex","time":"15:54:55","quantity":0.0375,"buy":{"price":5733.03,"num":0.03756259,"total":215.34746559},"sell":{"price":5774.1,"num":0.0375,"total":216.1079623}},{"market":"BTC-USDT","percent":0.35,"profit":0.7605,"direction":"binance-poloniex","time":"15:54:58","quantity":0.0375,"buy":{"price":5733.03,"num":0.03756259,"total":215.34746559},"sell":{"price":5774.1,"num":0.0375,"total":216.1079623}},{"market":"BTC-USDT","percent":0.35,"profit":0.7605,"direction":"binance-poloniex","time":"15:55:02","quantity":0.0375,"buy":{"price":5733.03,"num":0.03756259,"total":215.34746559},"sell":{"price":5774.1,"num":0.0375,"total":216.1079623}},{"market":"BTC-USDT","percent":0.35,"profit":0.7605,"direction":"binance-poloniex","time":"15:55:05","quantity":0.0375,"buy":{"price":5733.03,"num":0.03756259,"total":215.34746559},"sell":{"price":5774.1,"num":0.0375,"total":216.1079623}},{"market":"BTC-USDT","percent":0.35,"profit":0.7605,"direction":"binance-poloniex","time":"15:55:09","quantity":0.0375,"buy":{"price":5733.03,"num":0.03756259,"total":215.34746559},"sell":{"price":5774.1,"num":0.0375,"total":216.1079623}},{"market":"BTC-USDT","percent":0.35,"profit":0.7605,"direction":"binance-poloniex","time":"15:55:12","quantity":0.0375,"buy":{"price":5733.03,"num":0.03756259,"total":215.34746559},"sell":{"price":5774.1,"num":0.0375,"total":216.1079623}},{"market":"BTC-USDT","percent":0.35,"profit":0.7605,"direction":"binance-poloniex","time":"15:55:15","quantity":0.0375,"buy":{"price":5733.03,"num":0.03756259,"total":215.34746559},"sell":{"price":5774.1,"num":0.0375,"total":216.1079623}},{"market":"BTC-USDT","percent":0.35,"profit":0.7605,"direction":"binance-poloniex","time":"15:55:19","quantity":0.0375,"buy":{"price":5733.03,"num":0.03756259,"total":215.34746559},"sell":{"price":5774.1,"num":0.0375,"total":216.1079623}},{"market":"BTC-USDT","percent":0.35,"profit":0.7605,"direction":"binance-poloniex","time":"15:55:22","quantity":0.0375,"buy":{"price":5733.03,"num":0.03756259,"total":215.34746559},"sell":{"price":5774.1,"num":0.0375,"total":216.1079623}},{"market":"BTC-USDT","percent":0.35,"profit":0.7605,"direction":"binance-poloniex","time":"15:55:26","quantity":0.0375,"buy":{"price":5733.03,"num":0.03756259,"total":215.34746559},"sell":{"price":5774.1,"num":0.0375,"total":216.1079623}},{"market":"BTC-USDT","percent":0.35,"profit":0.7605,"direction":"binance-poloniex","time":"15:55:29","quantity":0.0375,"buy":{"price":5733.03,"num":0.03756259,"total":215.34746559},"sell":{"price":5774.1,"num":0.0375,"total":216.1079623}},{"market":"BTC-USDT","percent":0.35,"profit":0.7605,"direction":"binance-poloniex","time":"15:55:33","quantity":0.0375,"buy":{"price":5733.03,"num":0.03756259,"total":215.34746559},"sell":{"price":5774.1,"num":0.0375,"total":216.1079623}},{"market":"BTC-USDT","percent":0.35,"profit":0.7605,"direction":"binance-poloniex","time":"15:55:36","quantity":0.0375,"buy":{"price":5733.03,"num":0.03756259,"total":215.34746559},"sell":{"price":5774.1,"num":0.0375,"total":216.1079623}},{"market":"BTC-USDT","percent":0.35,"profit":0.1521,"direction":"binance-poloniex","time":"15:56:28","quantity":0.0075,"buy":{"price":5733.03,"num":0.00751252,"total":43.06949312},"sell":{"price":5774.1,"num":0.0075,"total":43.22159246}},{"market":"BTC-USDT","percent":0.35,"profit":0.1521,"direction":"binance-poloniex","time":"15:56:31","quantity":0.0075,"buy":{"price":5733.03,"num":0.00751252,"total":43.06949312},"sell":{"price":5774.1,"num":0.0075,"total":43.22159246}},{"market":"BTC-USDT","percent":0.35,"profit":0.1521,"direction":"binance-poloniex","time":"15:56:35","quantity":0.0075,"buy":{"price":5733.03,"num":0.00751252,"total":43.06949312},"sell":{"price":5774.1,"num":0.0075,"total":43.22159246}},{"market":"BTC-USDT","percent":0.35,"profit":0.1521,"direction":"binance-poloniex","time":"15:56:38","quantity":0.0075,"buy":{"price":5733.03,"num":0.00751252,"total":43.06949312},"sell":{"price":5774.1,"num":0.0075,"total":43.22159246}},{"market":"BTC-USDT","percent":0.35,"profit":0.1521,"direction":"binance-poloniex","time":"15:56:42","quantity":0.0075,"buy":{"price":5733.03,"num":0.00751252,"total":43.06949312},"sell":{"price":5774.1,"num":0.0075,"total":43.22159246}},{"market":"BTC-USDT","percent":0.35,"profit":0.1521,"direction":"binance-poloniex","time":"15:56:45","quantity":0.0075,"buy":{"price":5733.03,"num":0.00751252,"total":43.06949312},"sell":{"price":5774.1,"num":0.0075,"total":43.22159246}},{"market":"BTC-USDT","percent":0.35,"profit":0.1521,"direction":"binance-poloniex","time":"15:56:48","quantity":0.0075,"buy":{"price":5733.03,"num":0.00751252,"total":43.06949312},"sell":{"price":5774.1,"num":0.0075,"total":43.22159246}},{"market":"BTC-USDT","percent":0.35,"profit":0.1521,"direction":"binance-poloniex","time":"15:56:52","quantity":0.0075,"buy":{"price":5733.03,"num":0.00751252,"total":43.06949312},"sell":{"price":5774.1,"num":0.0075,"total":43.22159246}},{"market":"BTC-USDT","percent":0.35,"profit":0.1521,"direction":"binance-poloniex","time":"15:56:55","quantity":0.0075,"buy":{"price":5733.03,"num":0.00751252,"total":43.06949312},"sell":{"price":5774.1,"num":0.0075,"total":43.22159246}},{"market":"BTC-USDT","percent":0.35,"profit":0.1521,"direction":"binance-poloniex","time":"15:56:59","quantity":0.0075,"buy":{"price":5733.03,"num":0.00751252,"total":43.06949312},"sell":{"price":5774.1,"num":0.0075,"total":43.22159246}},{"market":"BTC-USDT","percent":0.35,"profit":0.7605,"direction":"binance-poloniex","time":"15:57:02","quantity":0.0375,"buy":{"price":5733.03,"num":0.03756259,"total":215.34746559},"sell":{"price":5774.1,"num":0.0375,"total":216.10796232}},{"market":"BTC-USDT","percent":0.35,"profit":1.8252,"direction":"binance-poloniex","time":"15:57:05","quantity":0.09000000000000002,"buy":{"price":5733.03,"num":0.09015022,"total":516.83391741},"sell":{"price":5774.1,"num":0.09,"total":518.65910956}},{"market":"BTC-USDT","percent":0.35,"profit":0.7605,"direction":"binance-poloniex","time":"15:57:09","quantity":0.0375,"buy":{"price":5733.03,"num":0.03756259,"total":215.34746559},"sell":{"price":5774.1,"num":0.0375,"total":216.10796232}},{"market":"BTC-USDT","percent":0.35,"profit":0.1521,"direction":"binance-poloniex","time":"15:57:12","quantity":0.0075,"buy":{"price":5733.03,"num":0.00751252,"total":43.06949312},"sell":{"price":5774.1,"num":0.0075,"total":43.22159246}},{"market":"BTC-USDT","percent":0.35,"profit":0.1521,"direction":"binance-poloniex","time":"15:57:15","quantity":0.0075,"buy":{"price":5733.03,"num":0.00751252,"total":43.06949312},"sell":{"price":5774.1,"num":0.0075,"total":43.22159246}},{"market":"BTC-USDT","percent":0.35,"profit":0.1521,"direction":"binance-poloniex","time":"15:57:19","quantity":0.0075,"buy":{"price":5733.03,"num":0.00751252,"total":43.06949312},"sell":{"price":5774.1,"num":0.0075,"total":43.22159246}},{"market":"BTC-USDT","percent":0.35,"profit":0.1521,"direction":"binance-poloniex","time":"15:57:22","quantity":0.0075,"buy":{"price":5733.03,"num":0.00751252,"total":43.06949312},"sell":{"price":5774.1,"num":0.0075,"total":43.22159246}},{"market":"BTC-USDT","percent":0.35,"profit":0.1521,"direction":"binance-poloniex","time":"15:57:26","quantity":0.0075,"buy":{"price":5733.03,"num":0.00751252,"total":43.06949312},"sell":{"price":5774.1,"num":0.0075,"total":43.22159246}},{"market":"BTC-USDT","percent":0.35,"profit":0.1521,"direction":"binance-poloniex","time":"15:57:29","quantity":0.0075,"buy":{"price":5733.03,"num":0.00751252,"total":43.06949312},"sell":{"price":5774.1,"num":0.0075,"total":43.22159246}},{"market":"BTC-USDT","percent":0.35,"profit":0.1521,"direction":"binance-poloniex","time":"15:57:32","quantity":0.0075,"buy":{"price":5733.03,"num":0.00751252,"total":43.06949312},"sell":{"price":5774.1,"num":0.0075,"total":43.22159246}},{"market":"BTC-USDT","percent":0.35,"profit":0.1521,"direction":"binance-poloniex","time":"15:57:36","quantity":0.0075,"buy":{"price":5733.03,"num":0.00751252,"total":43.06949312},"sell":{"price":5774.1,"num":0.0075,"total":43.22159246}},{"market":"BTC-USDT","percent":0.35,"profit":0.1521,"direction":"binance-poloniex","time":"15:57:39","quantity":0.0075,"buy":{"price":5733.03,"num":0.00751252,"total":43.06949312},"sell":{"price":5774.1,"num":0.0075,"total":43.22159246}},{"market":"BTC-USDT","percent":0.35,"profit":0.1521,"direction":"binance-poloniex","time":"15:57:43","quantity":0.0075,"buy":{"price":5733.03,"num":0.00751252,"total":43.06949312},"sell":{"price":5774.1,"num":0.0075,"total":43.22159246}},{"market":"BTC-USDT","percent":0.35,"profit":0.1521,"direction":"binance-poloniex","time":"15:57:46","quantity":0.0075,"buy":{"price":5733.03,"num":0.00751252,"total":43.06949312},"sell":{"price":5774.1,"num":0.0075,"total":43.22159246}},{"market":"BTC-USDT","percent":0.34,"profit":0.1449,"direction":"binance-poloniex","time":"15:57:49","quantity":0.0075,"buy":{"price":5733.03,"num":0.00751252,"total":43.06949312},"sell":{"price":5770.71,"num":0.0075,"total":43.21441229}},{"market":"BTC-USDT","percent":0.34,"profit":0.1449,"direction":"binance-poloniex","time":"15:57:53","quantity":0.0075,"buy":{"price":5733.03,"num":0.00751252,"total":43.06949312},"sell":{"price":5770.71,"num":0.0075,"total":43.21441229}},{"market":"BTC-USDT","percent":0.3,"profit":0.128,"direction":"binance-poloniex","time":"15:57:56","quantity":0.0075,"buy":{"price":5733.03,"num":0.00751252,"total":43.06949312},"sell":{"price":5770.71,"num":0.0075,"total":43.19749523}},{"market":"BTC-USDT","percent":0.3,"profit":0.128,"direction":"binance-poloniex","time":"15:58:00","quantity":0.0075,"buy":{"price":5733.03,"num":0.00751252,"total":43.06949312},"sell":{"price":5770.71,"num":0.0075,"total":43.19749523}},{"market":"BTC-USDT","percent":0.3,"profit":0.128,"direction":"binance-poloniex","time":"15:58:03","quantity":0.0075,"buy":{"price":5733.03,"num":0.00751252,"total":43.06949312},"sell":{"price":5770.71,"num":0.0075,"total":43.19749523}},{"market":"BTC-USDT","percent":0.35,"profit":0.4476,"direction":"binance-poloniex","time":"16:21:40","quantity":0.0225,"buy":{"price":5714.5,"num":0.02253756,"total":128.79085846},"sell":{"price":5755.12,"num":0.0225,"total":129.23849615}},{"market":"BTC-USDT","percent":0.35,"profit":0.4476,"direction":"binance-poloniex","time":"16:21:43","quantity":0.0225,"buy":{"price":5714.5,"num":0.02253756,"total":128.79085846},"sell":{"price":5755.12,"num":0.0225,"total":129.23849615}},{"market":"BTC-USDT","percent":0.35,"profit":0.4476,"direction":"binance-poloniex","time":"16:21:47","quantity":0.0225,"buy":{"price":5714.5,"num":0.02253756,"total":128.79085846},"sell":{"price":5755.12,"num":0.0225,"total":129.23849615}},{"market":"BTC-USDT","percent":0.34,"profit":0.4364,"direction":"binance-poloniex","time":"16:26:27","quantity":0.0225,"buy":{"price":5715,"num":0.02253756,"total":128.80212724},"sell":{"price":5755.12,"num":0.0225,"total":129.23849616}}],"binance-bittrex":[]}}